scbsp/__init__.py
scbsp/scbsp.py
scbsp-0.3.2.dist-info/licenses/LICENSE
scbsp-0.3.2.dist-info/METADATA
scbsp-0.3.2.dist-info/WHEEL
scbsp-0.3.2.dist-info/top_level.txt
scbsp-0.3.2.dist-info/RECORD
