Metadata-Version: 2.4
Name: scbsp
Version: 0.3.2
Summary: A package that efficiently computes p-values for a given set of genes based on input matrices representing cell coordinates and gene expression data
Home-page: https://github.com/YQ-Wang/scBSP
Author: Yiqing Wang, Jinpu Li
Author-email: yqw@wangemail.com, lijinp@health.missouri.edu
License: GPLv3
Classifier: License :: OSI Approved :: GNU General Public License v3 (GPLv3)
Classifier: Programming Language :: Python :: 3
Classifier: Programming Language :: Python :: 3.10
Classifier: Programming Language :: Python :: 3.11
Classifier: Programming Language :: Python :: 3.12
Classifier: Programming Language :: Python :: 3.13
Classifier: Operating System :: OS Independent
Requires-Python: >=3.10
License-File: LICENSE
Requires-Dist: numpy>=1.24.4
Requires-Dist: pandas>=1.3.5
Requires-Dist: scipy>=1.10.1
Requires-Dist: scikit-learn>=1.3.2
Provides-Extra: gpu
Requires-Dist: torch>=1.10.0; extra == "gpu"
Dynamic: author
Dynamic: author-email
Dynamic: classifier
Dynamic: description
Dynamic: description-content-type
Dynamic: home-page
Dynamic: license
Dynamic: license-file
Dynamic: provides-extra
Dynamic: requires-dist
Dynamic: requires-python
Dynamic: summary
